mlfoundry_ui/__init__.py
mlfoundry_ui/__main__.py
mlfoundry_ui/cli/__init__.py
mlfoundry_ui/cli/cli_interface.py
mlfoundry_ui/constants.py
mlfoundry_ui/webapp/__init__.py
mlfoundry_ui/webapp/dashboard_constants.py
mlfoundry_ui/webapp/demo_explainability/__init__.py
mlfoundry_ui/webapp/demo_explainability/model_demo.py
mlfoundry_ui/webapp/main_app.py
mlfoundry_ui/webapp/mlfoundry_data.py
mlfoundry_ui/webapp/model_comparison/__init__.py
mlfoundry_ui/webapp/model_comparison/model_comparison.py
mlfoundry_ui/webapp/model_types/base_view.py
mlfoundry_ui/webapp/model_types/binary_classification_view.py
mlfoundry_ui/webapp/model_types/classification_view.py
mlfoundry_ui/webapp/model_types/multiclass_classification_view.py
mlfoundry_ui/webapp/model_types/regression_view.py
mlfoundry_ui/webapp/model_types/timeseries_view.py
mlfoundry_ui/webapp/model_view/__init__.py
mlfoundry_ui/webapp/model_view/data_health.py
mlfoundry_ui/webapp/model_view/feature_view.py
mlfoundry_ui/webapp/model_view/model_health.py
mlfoundry_ui/webapp/model_view/run_details.py
mlfoundry_ui/webapp/sidebar.py
mlfoundry_ui-0.1.5.dist-info/entry_points.txt
mlfoundry_ui-0.1.5.dist-info/WHEEL
mlfoundry_ui-0.1.5.dist-info/METADATA
mlfoundry_ui-0.1.5.dist-info/RECORD
