Metadata-Version: 2.1
Name: mlfoundry-ui
Version: 0.1.5
Summary: Dashboard code for mlfoundry
Home-page: https://github.com/truefoundry/mlfoundry-ui
Author: Abhishek Choudhary
Author-email: abhichoudhary06@gmail.com
Requires-Python: >=3.7,<3.10
Classifier: Programming Language :: Python :: 3
Classifier: Programming Language :: Python :: 3.7
Classifier: Programming Language :: Python :: 3.8
Classifier: Programming Language :: Python :: 3.9
Requires-Dist: hydralit (>=1.0.10,<2.0.0)
Requires-Dist: matplotlib (>=3.0.3)
Requires-Dist: mlfoundry (>=0.1.9)
Requires-Dist: numpy (>=1.17.0)
Requires-Dist: pandas (>=1.0.0)
Requires-Dist: plotly (>=5.5.0,<6.0.0)
Requires-Dist: streamlit (>=1.3.0,<2.0.0)
Requires-Dist: whylogs (>=0.6.15)
Project-URL: Repository, https://github.com/truefoundry/mlfoundry-ui
